{"id":"tprltbrqaq","title":"Watsonx Assistant Time Out WorkAround (using poling) ","documentationURL":"https://github.ibm.com/Client-Eng-EMEA-IN/WA_Middleware/blob/rag_cos/README.md","author":"Safalta Suresh, Aniket Mohan","categoryId":1,"description":"This asset provides a workaround for addressing the 30-second timeout issue of Watsonx Assistant by leveraging IBM COS (Cloud Object Storage).","typeId":1,"type":"python","fileName":"","source":"git","assetURL":"https://github.ibm.com/Client-Eng-EMEA-IN/WA_Middleware/tree/rag_cos","userId":"314d15d5-166c-4e11-a8d8-d265c8c894cb","preRequisites":{"fields":[],"requiredFields":[[]],"installDependencyCommands":[""]},"createdTimestamp":1725859092164,"updatedTimestamp":1725859092164}