{"id":"dhgrhddohw","title":"IBM TTS for Synthetic Audio","author":"Gautam Chutani","categoryId":12,"description":"IBM Text-to-Speech for generating synthetic audio samples using different languages and voices.","typeId":1,"type":"python","fileName":"dhgrhddohw.py","source":"local","assetURL":"","userId":"4038d64d-aa47-43c4-bad9-43c7cd3330d1","preRequisites":{"fields":[{"type":"text","label":"TTS_API_KEY"},{"type":"text","label":"TTS_URL"}],"requiredFields":[["tts_api_key","tts_url"]],"installDependencyCommands":["pip install ibm-watson","pip install ibm-cos-sdk","pip install pydub"]},"createdTimestamp":1719755083786,"updatedTimestamp":1719755896752}