{"id":"zaentmmrso","title":"Data Integration and Search in WatsonX Discovery using FAST API","documentationURL":"same","author":"Nagaraju Kuruva","categoryId":2,"description":"This asset enables data loading into WatsonX Discovery and allows data searching from WatsonX Discovery using FAST API.","typeId":1,"type":"python","fileName":"zaentmmrso.py","source":"local","assetURL":"","userId":"1925ef83-e37c-4930-8b19-422e55ccdfe9","preRequisites":{"fields":[],"requiredFields":[[]],"installDependencyCommands":[""]},"createdTimestamp":1727955270432,"updatedTimestamp":1727955270432}