{
    "id": "102",
    "author" : "nupur.negi2",
    "category": "CP4D",
    "title": "Get cp4d Services",
    "description": "List all services from cp4d cluster",
    "preRequisites": {
        "fields": [
            {
                "type": "text",
                "label": "OC Login"
            },
            {
                "type": "text",
                "label": "Project Name"
            }
        ],
        "requiredFields": [
            [
                "oc_login",
                "project_name"
            ]
        ],
        "installDependencyCommands": ["pip3 install pandas", "apt-get install jq -y"]
    },
    "fileName": "get-services.sh",
    "type": "bash"
}
